src/control_unit.sv
module control_unit (output logic [1:0] PCSrc, 
                    output logic [1:0] ResultSrc,
                    output logic MemWrite, ALUSrc, RegWrite,
                    output logic [4:0] ALUControl,
                    output logic [2:0] ImmSrc,
                    input logic [31:0] Instr,
                    input logic Zero, Negative);

// Extract fields from the instruction
  logic [6:0] opcode;
  logic [2:0] funct3;
  logic       funct7_bit;
  
  assign opcode    = Instr[6:0];    // opcode field
  assign funct3    = Instr[14:12];  // funct3 field
  assign funct7_bit= Instr[30];     // funct7[5] bit (for add/sub distinction)

  always_comb begin
    // Default control signal values:
    PCSrc     = 2'b00;      // Next instruction (PC+4)
    ResultSrc = 2'b00;      // Default: ALU result
    MemWrite  = 0;
    ALUSrc    = 0;          // Default: use register operand
    RegWrite  = 0;
    ALUControl= 5'b00010;   // Default: addition (5'b00010)
    ImmSrc    = 3'b000;     // Default: I-Type immediate

    case (opcode)
      // R-Type Instructions (Register-Register ALU operations)
      7'b0110011: begin 
          RegWrite = 1;
          ALUSrc   = 0; // use register operands
          case (funct3)
            3'b000: ALUControl = (funct7_bit) ? 5'b00001 : 5'b00010; // SUB if funct7=1, ADD if not
            3'b110: ALUControl = 5'b00111; // OR
            3'b111: ALUControl = 5'b00011; // AND
            3'b001: ALUControl = 5'b00000; // SLL
            3'b101: ALUControl = 5'b10000; // SRL
            3'b010: ALUControl = 5'b01010; // SLT
            default: ALUControl = 5'b00010; // Default to addition
          endcase
      end

      // I-Type Instructions (Immediate ALU operations & Loads)
      7'b0010011: begin 
          RegWrite = 1;
          ALUSrc   = 1; // immediate
          ImmSrc   = 3'b000; // I-Type immediate
          case (funct3)
            3'b000: ALUControl = 5'b00010; // ADDI: addition
            3'b110: ALUControl = 5'b00111; // ORI
            3'b111: ALUControl = 5'b00011; // ANDI
            3'b001: ALUControl = 5'b00000; // SLLI: shift left
            3'b101: ALUControl = 5'b10000; // SRLI: shift right logical
            3'b010: ALUControl = 5'b01010; // SLTI: set less than
            default: ALUControl = 5'b00010;
          endcase
      end

      // Load Word (LW)
      7'b0000011: begin 
          RegWrite = 1;
          ALUSrc   = 1;      // Use immediate offset
          ImmSrc   = 3'b000; // I-Type immediate
          ResultSrc= 2'b01;  // Data from memory
          ALUControl = 5'b00010; // Addition for address calculation
      end

      // Store Word (SW)
      7'b0100011: begin 
          MemWrite = 1;
          ALUSrc   = 1;      // Use immediate offset
          ImmSrc   = 3'b001; // S-Type immediate
          ALUControl = 5'b00010; // Addition for address calculation
      end

      // Branch Instructions (BEQ, BNE, BLT, BGE)
      7'b1100011: begin 
          ALUSrc   = 0;       // Compare registers
          ImmSrc   = 3'b010;   // B-Type immediate
          ALUControl = 5'b00001; // Subtraction for comparison
          case (funct3)
            3'b000: if (Zero) PCSrc = 2'b01; // BEQ: branch if equal
            3'b001: if (!Zero) PCSrc = 2'b01; // BNE: branch if not equal
            3'b100: if (Negative) PCSrc = 2'b01; // BLT: branch if less than
            3'b101: if (!Negative || Zero) PCSrc = 2'b01; // BGE: branch if greater or equal
            default: PCSrc = 2'b00;
          endcase
      end

      // Jump and Link (JAL)
      7'b1101111: begin 
          PCSrc    = 2'b01;   // Jump to target address
          RegWrite = 1;       // Write PC+4 to register
          ResultSrc= 2'b10;   // Use PC+4 as write-back data
          ImmSrc   = 3'b100;   // J-Type immediate
          ALUControl = 5'b00010; // Addition (for PC+4 calculation)
      end

      // Jump and Link Register (JALR)
      7'b1100111: begin 
          PCSrc    = 2'b10;   // Jump to computed address
          RegWrite = 1;       // Write PC+4 to register
          ResultSrc= 2'b10;   // Use PC+4 as write-back data
          ImmSrc   = 3'b000;   // I-Type immediate
          ALUControl = 5'b00010; // Addition (for PC+4 calculation)
      end

      // Load Upper Immediate (LUI)
      7'b0110111: begin 
          RegWrite = 1;
          ImmSrc   = 3'b011;   // U-Type immediate
          ResultSrc= 2'b11;    // Load immediate directly
          ALUControl = 5'b11111; // For LUI, the ALU just outputs the immediate shifted
      end

      default: begin
          // Keep default values
      end
    endcase
  end
endmodule

tb/control_unit_tb.sv
`timescale 1ns/1ps
`include "control_unit.sv"

// control_unit_tb.sv - Testbench for control_unit
module control_unit_tb;
    logic [1:0] PCSrc, ResultSrc;
    logic MemWrite, ALUSrc, RegWrite;
    logic [4:0] ALUControl;
    logic [2:0] ImmSrc;
    logic [31:0] Instr;
    logic Zero, Negative;

    // Instantiate DUT (Device Under Test)
    control_unit dut (
        .PCSrc(PCSrc),
        .ResultSrc(ResultSrc),
        .MemWrite(MemWrite),
        .ALUSrc(ALUSrc),
        .RegWrite(RegWrite),
        .ALUControl(ALUControl),
        .ImmSrc(ImmSrc),
        .Instr(Instr),
        .Zero(Zero),
        .Negative(Negative)
    );

    // Test Procedure
    initial begin
        $dumpfile("control_unit_tb.vcd");
        $dumpvars(0, control_unit_tb);
        
        $monitor("t = %3d | Instr = %h | PCSrc = %b | ALUControl = %b | ALUSrc = %b | RegWrite = %b | MemWrite = %b | ResultSrc = %b | ImmSrc = %b",
         $time, Instr, PCSrc, ALUControl, ALUSrc, RegWrite, MemWrite, ResultSrc, ImmSrc);
        
        // Test ADDI (Immediate Addition)
        Instr = 32'h03200093; // addi x1, x0, 50
        #10;

        // Test LW (Load Word)
        Instr = 32'hffc02103; // lw x2, -4(x0)
        #10;

        // Test SUB (Subtract)
        Instr = 32'h402081b3; // sub x3, x1, x2
        #10;

        // Test SW (Store Word)
        Instr = 32'hfe302e23; // sw x3, -4(x0)
        #10;

        // Test BEQ (Branch if Equal)
        Instr = 32'h00000063; // beq x0, x0, 0
        Zero = 1; // Assign only when needed
        #10;

        // Test JAL (Jump and Link)
        Instr = 32'h000000ef; // jal x1, offset
        #10;

        // Test JALR (Jump and Link Register)
        Instr = 32'h000100e7; // jalr x1, offset(x2)
        #10;

        // Test LUI (Load Upper Immediate)
        Instr = 32'h00001037; // lui x2, imm
        #10;

        $display("All tests completed.");
        $finish;
    end
endmodule

sim/control_unit_tb.vcd
$date
	Thu Mar 13 16:43:47 2025
$end
$version
	Icarus Verilog
$end
$timescale
	1ps
$end
$scope module control_unit_tb $end
$var wire 2 ! ResultSrc [1:0] $end
$var wire 1 " RegWrite $end
$var wire 2 # PCSrc [1:0] $end
$var wire 1 $ MemWrite $end
$var wire 3 % ImmSrc [2:0] $end
$var wire 1 & ALUSrc $end
$var wire 5 ' ALUControl [4:0] $end
$var reg 32 ( Instr [31:0] $end
$var reg 1 ) Negative $end
$var reg 1 * Zero $end
$scope module dut $end
$var wire 32 + Instr [31:0] $end
$var wire 1 ) Negative $end
$var wire 1 * Zero $end
$var wire 7 , opcode [6:0] $end
$var wire 1 - funct7_bit $end
$var wire 3 . funct3 [2:0] $end
$var reg 5 / ALUControl [4:0] $end
$var reg 1 & ALUSrc $end
$var reg 3 0 ImmSrc [2:0] $end
$var reg 1 $ MemWrite $end
$var reg 2 1 PCSrc [1:0] $end
$var reg 1 " RegWrite $end
$var reg 2 2 ResultSrc [1:0] $end
$upscope $end
$upscope $end
$enddefinitions $end
#0
$dumpvars
b0 2
b0 1
b0 0
b10 /
b0 .
0-
b10011 ,
b11001000000000000010010011 +
x*
x)
b11001000000000000010010011 (
b10 '
1&
b0 %
0$
b0 #
1"
b0 !
$end
#10000
b1 !
b1 2
1"
1&
b11 ,
b10 .
1-
b11111111110000000010000100000011 (
b11111111110000000010000100000011 +
#20000
b1 '
b1 /
1"
0&
b0 !
b0 2
b110011 ,
b0 .
b1000000001000001000000110110011 (
b1000000001000001000000110110011 +
#30000
b1 %
b1 0
1&
1$
b10 '
b10 /
0"
b100011 ,
b10 .
b11111110001100000010111000100011 (
b11111110001100000010111000100011 +
#40000
b1 #
b1 1
b1 '
b1 /
b10 %
b10 0
0&
0$
b1100011 ,
b0 .
0-
1*
b1100011 (
b1100011 +
#50000
b10 !
b10 2
1"
b100 %
b100 0
b10 '
b10 /
b1 #
b1 1
b1101111 ,
b11101111 (
b11101111 +
#60000
b0 %
b0 0
1"
b10 !
b10 2
b10 #
b10 1
b1100111 ,
b10000000011100111 (
b10000000011100111 +
#70000
b11111 '
b11111 /
b11 %
b11 0
1"
b11 !
b11 2
b0 #
b0 1
b110111 ,
b1 .
b1000000110111 (
b1000000110111 +
