src/program_counter.sv
module program_counter (output logic [31:0] PC, PCPlus4,
                        input logic [31:0] PCTarget, ALUResult,
                        input logic [1:0] PCSrc,
                        input logic Reset, CLK);


logic [31:0] pc_reg; // Internal register to hold PC value

    // PC update logic (synchronous reset and clock edge-triggered)
    always_ff @(posedge CLK) begin
        if (Reset)
            pc_reg <= 32'h00000000; // Reset PC to 0x00000000
        else begin
            case (PCSrc)
                2'b00: pc_reg <= pc_reg + 4;   // Normal increment (for sequential execution)
                2'b01: pc_reg <= PCTarget;     // Branch target address (for beq, bne, blt, bge)
                2'b10: pc_reg <= ALUResult;    // JALR (Jump Register target)
                default: pc_reg <= pc_reg + 4; // Default to sequential execution
            endcase
        end
    end

    // Assign outputs
    assign PC = pc_reg;
    assign PCPlus4 = pc_reg + 4; // Always compute PC + 4

endmodule

tb/program_counter_tb.sv
`timescale 1ns/1ps
`include "program_counter.sv"


// program_counter_tb.sv - Testbench for program_counter
module program_counter_tb;
    logic [31:0] PC, PCPlus4;
    logic [31:0] PCTarget, ALUResult;
    logic [1:0] PCSrc;
    logic Reset, CLK;
   
    // Instantiate the DUT (Device Under Test)
    program_counter dut (
        .PC(PC),
        .PCPlus4(PCPlus4),
        .PCTarget(PCTarget),
        .ALUResult(ALUResult),
        .PCSrc(PCSrc),
        .Reset(Reset),
        .CLK(CLK)
    );
   
    // Clock Generation (10ns period)
    always #5 CLK = ~CLK;
   
    initial begin
        $dumpfile("program_counter_tb.vcd");
        $dumpvars(0, program_counter_tb);
        $monitor("t = %3d, PC = %h, PCPlus4 = %h, PCSrc = %b", $time, PC, PCPlus4, PCSrc);
       
        // Initialize signals
        CLK = 0; 
        Reset = 1; 
        PCSrc = 2'b00; 
        PCTarget = 32'h00000010;
        ALUResult = 32'h00000040;
        
        #10 Reset = 0;  // Release reset

        // Case 1: PCSrc = 00 (Sequential execution)
        #10 PCSrc = 2'b00;
        
        // Case 2: PCSrc = 01 (Branching)
        #10 PCSrc = 2'b01;
        #10 PCTarget = 32'h00000020; // Change target for demonstration
        
        // Case 3: PCSrc = 10 (Jump Register)
        #10 PCSrc = 2'b10;
        #10 ALUResult = 32'h00000040; // Change ALU result for demonstration

        // End simulation
        #10 $finish;
    end
endmodule

sim/program_counter_tb.vcd
$date
	Thu Mar 13 16:41:06 2025
$end
$version
	Icarus Verilog
$end
$timescale
	1ps
$end
$scope module program_counter_tb $end
$var wire 32 ! PCPlus4 [31:0] $end
$var wire 32 " PC [31:0] $end
$var reg 32 # ALUResult [31:0] $end
$var reg 1 $ CLK $end
$var reg 2 % PCSrc [1:0] $end
$var reg 32 & PCTarget [31:0] $end
$var reg 1 ' Reset $end
$scope module dut $end
$var wire 32 ( ALUResult [31:0] $end
$var wire 1 $ CLK $end
$var wire 32 ) PC [31:0] $end
$var wire 2 * PCSrc [1:0] $end
$var wire 32 + PCTarget [31:0] $end
$var wire 1 ' Reset $end
$var wire 32 , PCPlus4 [31:0] $end
$var reg 32 - pc_reg [31:0] $end
$upscope $end
$upscope $end
$enddefinitions $end
#0
$dumpvars
bx -
bx ,
b10000 +
b0 *
bx )
b1000000 (
1'
b10000 &
b0 %
0$
b1000000 #
bx "
bx !
$end
#5000
b100 !
b100 ,
b0 "
b0 )
b0 -
1$
#10000
0$
0'
#15000
b1000 !
b1000 ,
b100 "
b100 )
b100 -
1$
#20000
0$
#25000
b1100 !
b1100 ,
b1000 "
b1000 )
b1000 -
1$
#30000
0$
b1 %
b1 *
#35000
b10100 !
b10100 ,
b10000 "
b10000 )
b10000 -
1$
#40000
0$
b100000 &
b100000 +
#45000
b100100 !
b100100 ,
b100000 "
b100000 )
b100000 -
1$
#50000
0$
b10 %
b10 *
#55000
b1000100 !
b1000100 ,
b1000000 "
b1000000 )
b1000000 -
1$
